nanobind_stubgen/NanobindStubsGenerator.py
nanobind_stubgen/__init__.py
nanobind_stubgen/__main__.py
nanobind_stubgen/utils.py
nanobind_stubgen-0.1.5.dist-info/LICENSE
nanobind_stubgen-0.1.5.dist-info/METADATA
nanobind_stubgen-0.1.5.dist-info/WHEEL
nanobind_stubgen-0.1.5.dist-info/entry_points.txt
nanobind_stubgen-0.1.5.dist-info/top_level.txt
nanobind_stubgen-0.1.5.dist-info/RECORD
