Metadata-Version: 2.1
Name: nanobind-stubgen
Version: 0.1.5
Summary: Generate python stub files for code completion in IDEs for nanobind modules.
Home-page: https://github.com/cansik/nanobind-stubgen
Author: Florian Bruggisser
Author-email: github@broox.ch
License: MIT license
Platform: UNKNOWN
License-File: LICENSE
